sigmoidal/__init__.py
Sigmoidal-0.4.0.dist-info/LICENSE
Sigmoidal-0.4.0.dist-info/METADATA
Sigmoidal-0.4.0.dist-info/WHEEL
Sigmoidal-0.4.0.dist-info/top_level.txt
Sigmoidal-0.4.0.dist-info/RECORD
