Metadata-Version: 2.1
Name: Sigmoidal
Version: 0.4.0
Summary: Sigmoidal is a small library to allow you to fit and evaluate sigmoid functions in a way that works like the Numpy Polynomial class.
Home-page: https://github.com/HelloSleuth/sigmoid
Author: Jade Glaze, Sleuth
Author-email: jade@hellosleuth.com
License: MIT
Classifier: License :: OSI Approved :: MIT License
Classifier: Programming Language :: Python :: 3.10
License-File: LICENSE
Requires-Dist: numpy (>=1.24.3)
Requires-Dist: scipy (>=1.10.1)
